setup.py
libagents/__init__.py
libagents/agents.py
libagents.egg-info/PKG-INFO
libagents.egg-info/SOURCES.txt
libagents.egg-info/dependency_links.txt
libagents.egg-info/top_level.txt