Metadata-Version: 1.0
Name: libagents
Version: 0.1.1
Summary: queue tasks to be done later
Home-page: http://github.com/snickers10m/lagents
Author: Charlie Morley
Author-email: charlie@gmail.com
License: MIT
Platform: UNKNOWN
